vaportrails/__init__.py
vaportrails-0.0.1.dist-info/licenses/LICENSE
vaportrails-0.0.1.dist-info/METADATA
vaportrails-0.0.1.dist-info/WHEEL
vaportrails-0.0.1.dist-info/top_level.txt
vaportrails-0.0.1.dist-info/RECORD
