Metadata-Version: 2.4
Name: vaportrails
Version: 0.0.1
Summary: Reserved namespace for the future Vaportrails developer flight recorder.
Author: Tyler Hughes
License: MIT
Project-URL: Homepage, https://github.com/tylerbrianhughes/vaportrails
Project-URL: Source, https://github.com/tylerbrianhughes/vaportrails
Classifier: Development Status :: 2 - Pre-Alpha
Classifier: Programming Language :: Python :: 3
Classifier: License :: OSI Approved :: MIT License
Requires-Python: >=3.9
License-File: LICENSE
Dynamic: license-file
